syncwrap/__init__.py
syncwrap/syncwrap.py
syncwrap-0.0.1.dist-info/LICENSE
syncwrap-0.0.1.dist-info/METADATA
syncwrap-0.0.1.dist-info/WHEEL
syncwrap-0.0.1.dist-info/top_level.txt
syncwrap-0.0.1.dist-info/RECORD
