Metadata-Version: 2.1
Name: syncwrap
Version: 0.0.1
Summary: A simple python library providing a function decorator to wap async functions for use in synchronous code
Home-page: https://github.com/Bearddyy/syncwrap
Author: Daniel Byrne
Author-email: byrne_daniel@hotmail.co.uk
License: Apache 2.0
Requires-Python: >=3.6
License-File: LICENSE
Requires-Dist: asyncio
Requires-Dist: typing-extensions ; python_version < "3.8"
